{
    "url": "http://intelligencesquaredus.org/debates/past-debates/item/768-ration-end-of-life-care",
    "image-url": "http://intelligencesquaredus.org/images/debates/upcoming/EndOfife%20Debate/EndOfLifeWeb2.jpg",
    "date": "2012-10-10",
    "day": "Wednesday",
    "topic": "Ration End-Of-Life Care",
    "moderator": "John Donvan",
    "pre-debate": {
        "for": 43,
        "against": 22,
        "undecided": 35
    },
    "post-debate": {
        "for": 81,
        "against": 12,
        "undecided": 7
    },
    "winner": "for"
}